.hgignore
.hgtags
HISTORY.rst
LICENSE.txt
MANIFEST.in
Makefile
README-devel.rst
README.rst
mercurial_keyring.py
pytype.cfg
setup.py
mercurial_keyring.egg-info/PKG-INFO
mercurial_keyring.egg-info/SOURCES.txt
mercurial_keyring.egg-info/dependency_links.txt
mercurial_keyring.egg-info/requires.txt
mercurial_keyring.egg-info/top_level.txt
mercurial_keyring.egg-info/zip-safe
tests/backend/auth_hg_serve.cfg
tests/backend/auth_hg_serve.py